sprayer/__init__.py
sprayer/__main__.py
sprayer-0.9.1.dist-info/METADATA
sprayer-0.9.1.dist-info/WHEEL
sprayer-0.9.1.dist-info/entry_points.txt
sprayer-0.9.1.dist-info/top_level.txt
sprayer-0.9.1.dist-info/RECORD
