Metadata-Version: 2.1
Name: sprayer
Version: 0.9.1
Summary: UNKNOWN
Home-page: https://github.com/p0dalirius/Sprayer
Author: Podalirius
Author-email: podalirius@protonmail.com
License: GPL2
Platform: UNKNOWN
Classifier: Programming Language :: Python :: 3
Classifier: License :: OSI Approved :: GNU General Public License v2 (GPLv2)
Classifier: Operating System :: OS Independent
Requires-Python: >=3.6
Requires-Dist: impacket
Requires-Dist: sectools
